pastebot/__init__.py
pastebot/bot.py
pastebot/cli.py
pastebot/weibo.py
pastebot/rules/api.yar
pastebot/rules/api_keys.yar
pastebot/rules/emails.yar
pastebot/rules/hashes.yar
pastebot/rules/index.yar
pastebot/rules/private_keys.yar
pastebot-0.1.2.dist-info/DESCRIPTION.rst
pastebot-0.1.2.dist-info/METADATA
pastebot-0.1.2.dist-info/RECORD
pastebot-0.1.2.dist-info/WHEEL
pastebot-0.1.2.dist-info/entry_points.txt
pastebot-0.1.2.dist-info/metadata.json
pastebot-0.1.2.dist-info/top_level.txt
