Metadata-Version: 2.0
Name: pastebot
Version: 0.1.2
Summary: pastebot
Home-page: https://github.com/fate0/pastebot
Author: fate0
Author-email: fate0@fatezero.org
License: BSD license
Keywords: pastebot
Platform: UNKNOWN
Classifier: Development Status :: 2 - Pre-Alpha
Classifier: Intended Audience :: Developers
Classifier: License :: OSI Approved :: BSD License
Classifier: Natural Language :: English
Classifier: Programming Language :: Python :: 2
Classifier: Programming Language :: Python :: 2.7
Classifier: Programming Language :: Python :: 3
Classifier: Programming Language :: Python :: 3.4
Classifier: Programming Language :: Python :: 3.5
Classifier: Programming Language :: Python :: 3.6
Classifier: Topic :: Internet :: WWW/HTTP
Classifier: Topic :: Internet :: WWW/HTTP :: Browsers
Requires-Dist: click (==6.7)
Requires-Dist: raven (==6.1.0)
Requires-Dist: requests (==2.18.4)
Requires-Dist: yara-python (==3.6.3)
